django_pyc/__init__.py
django_pyc/management/__init__.py
django_pyc/management/commands/__init__.py
django_pyc/management/commands/clearpyc.py
django_pyc/management/commands/compilepyc.py
django_pyc-1.1.0.dist-info/LICENSE
django_pyc-1.1.0.dist-info/METADATA
django_pyc-1.1.0.dist-info/WHEEL
django_pyc-1.1.0.dist-info/top_level.txt
django_pyc-1.1.0.dist-info/RECORD
